electrify/__init__.py
electrify/ne_channel/ChannelConversations.py
electrify/ne_channel/MessageAttachments.py
electrify/ne_channel/__init__.py
electrify/ne_channel/chatwoot_client/__init__.py
electrify/ne_channel/chatwoot_client/__main__.py
electrify/ne_channel/chatwoot_client/action.py
electrify/ne_channel/chatwoot_client/http.py
electrify/ne_channel/chatwoot_client/definitions/__init__.py
electrify/ne_channel/chatwoot_client/definitions/actions.py
electrify/ne_channel/chatwoot_client/definitions/schemas/__init__.py
electrify/ne_channel/chatwoot_client/definitions/schemas/input_schemas.py
electrify/ne_channel/chatwoot_client/definitions/schemas/webhooks_events.py
electrify/ne_fuse/__init__.py
electrify/ne_work/__init__.py
electrify_sdk-0.1.1.dist-info/METADATA
electrify_sdk-0.1.1.dist-info/WHEEL
electrify_sdk-0.1.1.dist-info/top_level.txt
electrify_sdk-0.1.1.dist-info/RECORD
